[{"information":{"model":"1.0"},"online":true,"_id":"5cdbe47760fb3a0a55852850","eui64":"0x90FD9FFFFE5E1365","endpoint":1,"type":"0x0100","__v":0},{"information":{"model":"1.0"},"online":true,"_id":"5cdbe47b60fb3a0a55852851","eui64":"0x90FD9FFFFE1EB4D5","endpoint":1,"type":"0x0100","__v":0},{"information":{"model":"1.0"},"online":true,"_id":"5cdbe47b60fb3a0a55852852","eui64":"0x90FD9FFFFE1EB4D5","endpoint":2,"type":"0x0100","__v":0},{"information":{"model":"1.0"},"online":true,"_id":"5cdbe47c60fb3a0a55852853","eui64":"0x90FD9FFFFE1EB4D5","endpoint":3,"type":"0x0100","__v":0},{"information":{"model":"1.0"},"online":true,"_id":"5cdbe15b60fb3a0a5585283c","eui64":"0x000B57FFFE42980D","endpoint":1,"type":"0x0101","__v":0},{"information":{"model":"1.0"},"online":true,"_id":"5cdbe16660fb3a0a5585283d","eui64":"0x000B57FFFEA80A01","endpoint":1,"type":"0x0100","__v":0},{"information":{"model":"1.0"},"online":true,"_id":"5cdbe20860fb3a0a5585283e","eui64":"0x90FD9FFFFE21CC04","endpoint":1,"type":"0x0100","__v":0},{"information":{"model":"1.0"},"online":true,"_id":"5cdbe20860fb3a0a5585283f","eui64":"0x90FD9FFFFE21CC04","endpoint":2,"type":"0x0100","__v":0},{"information":{"model":"1.0"},"online":true,"_id":"5cdbe23b60fb3a0a55852840","eui64":"0x000B57FFFEA826F2","endpoint":1,"type":"0x0403","__v":0},{"information":{"model":"1.0"},"online":true,"_id":"5cdbe23b60fb3a0a55852841","eui64":"0x000B57FFFEA826F2","endpoint":2,"type":"0x0106","__v":0},{"information":{"model":"1.0"},"online":true,"_id":"5cdbe23b60fb3a0a55852842","eui64":"0x000B57FFFEA826F2","endpoint":3,"type":"0x0302","__v":0},{"information":{"model":"1.0"},"online":true,"_id":"5cdbe23b60fb3a0a55852843","eui64":"0x000B57FFFEA826F2","endpoint":4,"type":"0x0301","__v":0},{"information":{"model":"1.0"},"online":true,"_id":"5cdbe23b60fb3a0a55852844","eui64":"0x000B57FFFEA826F2","endpoint":5,"type":"0x0017","__v":0},{"information":{"model":"1.0"},"online":true,"_id":"5cdbe25960fb3a0a55852845","eui64":"0x000B57FFFEA8A5A0","endpoint":1,"type":"0x000A","__v":0},{"information":{"model":"1.0"},"online":true,"_id":"5cdbe25960fb3a0a55852846","eui64":"0x000B57FFFEA8A5A0","endpoint":2,"type":"0x0106","__v":0},{"information":{"model":"1.0"},"online":true,"_id":"5cdbe25960fb3a0a55852847","eui64":"0x000B57FFFEA8A5A0","endpoint":3,"type":"0x0302","__v":0},{"information":{"model":"1.0"},"online":true,"_id":"5cdbe25960fb3a0a55852848","eui64":"0x000B57FFFEA8A5A0","endpoint":4,"type":"0x0301","__v":0},{"information":{"model":"1.0"},"online":true,"_id":"5cdbe25960fb3a0a55852849","eui64":"0x000B57FFFEA8A5A0","endpoint":5,"type":"0x0017","__v":0},{"information":{"model":"1.0"},"online":true,"_id":"5cdbe39060fb3a0a5585284a","eui64":"0x000B57FFFE4285B5","endpoint":1,"type":"0x0100","__v":0},{"information":{"model":"1.0"},"online":true,"_id":"5cdbe39060fb3a0a5585284b","eui64":"0x000B57FFFE4285B5","endpoint":2,"type":"0x0103","__v":0},{"information":{"model":"1.0"},"online":true,"_id":"5cdbe40c60fb3a0a5585284c","eui64":"0x90FD9FFFFE21B38B","endpoint":1,"type":"0x0100","__v":0},{"information":{"model":"1.0"},"online":true,"_id":"5cdbe40c60fb3a0a5585284d","eui64":"0x90FD9FFFFE21B38B","endpoint":2,"type":"0x0100","__v":0},{"information":{"model":"1.0"},"online":true,"_id":"5cdbe40c60fb3a0a5585284e","eui64":"0x90FD9FFFFE21B38B","endpoint":3,"type":"0x0100","__v":0},{"information":{"model":"1.0"},"online":true,"_id":"5cdbe40c60fb3a0a5585284f","eui64":"0x90FD9FFFFE21B38B","endpoint":4,"type":"0x0100","__v":0}]